MANIFEST.in
README.rst
requirements-tests.txt
requirements.txt
setup.py
creh_logs.egg-info/PKG-INFO
creh_logs.egg-info/SOURCES.txt
creh_logs.egg-info/dependency_links.txt
creh_logs.egg-info/requires.txt
creh_logs.egg-info/top_level.txt
logs/__init__.py
logs/admin.py
logs/contstants.py
logs/models.py
logs/utils.py
logs/actions/__init__.py
logs/actions/register.py
logs/management/__init__.py
logs/management/commands/__init__.py
logs/management/commands/archived_logs.py
logs/management/commands/delete_logs.py
logs/migrations/0001_initial.py
logs/migrations/0002_log_user.py
logs/migrations/0003_auto_20170428_1105.py
logs/migrations/__init__.py
logs/tests/__init__.py
logs/tests/test_actions.py
logs/tests/test_commands.py
logs/tests/test_utils.py